pydantic_panel/__init__.py
pydantic_panel/dispatchers.py
pydantic_panel/numpy.py
pydantic_panel/pandas.py
pydantic_panel/pane.py
pydantic_panel/widgets.py
pydantic_panel-0.2.0.dist-info/AUTHORS.rst
pydantic_panel-0.2.0.dist-info/LICENSE
pydantic_panel-0.2.0.dist-info/METADATA
pydantic_panel-0.2.0.dist-info/WHEEL
pydantic_panel-0.2.0.dist-info/entry_points.txt
pydantic_panel-0.2.0.dist-info/RECORD
