Metadata-Version: 2.1
Name: pydantic_panel
Version: 0.2.0
Summary: Top-level package for pydantic-panel.
Home-page: https://github.com/jmosbacher/pydantic_panel
License: MIT
Author: Yossi Mosbacher
Author-email: joe.mosbacher@gmail.com
Requires-Python: >=3.8,<4.0
Classifier: Development Status :: 2 - Pre-Alpha
Classifier: Intended Audience :: Developers
Classifier: License :: OSI Approved :: MIT License
Classifier: Natural Language :: English
Classifier: Programming Language :: Python :: 3
Classifier: Programming Language :: Python :: 3.8
Classifier: Programming Language :: Python :: 3.9
Classifier: Programming Language :: Python :: 3.10
Classifier: Programming Language :: Python :: 3.11
Classifier: Programming Language :: Python :: 3.12
Requires-Dist: panel (>=0.13)
Requires-Dist: plum-dispatch
Requires-Dist: pydantic (>=2.0)
